fixed_vhd_writer/__init__.py
fixed_vhd_writer/cmd.py
fixed_vhd_writer/version.py
fixed_vhd_writer/vhd.py
fixed_vhd_writer-0.0.5.dist-info/LICENSE
fixed_vhd_writer-0.0.5.dist-info/METADATA
fixed_vhd_writer-0.0.5.dist-info/WHEEL
fixed_vhd_writer-0.0.5.dist-info/entry_points.txt
fixed_vhd_writer-0.0.5.dist-info/top_level.txt
fixed_vhd_writer-0.0.5.dist-info/RECORD
