Metadata-Version: 2.1
Name: fixed-vhd-writer
Version: 0.0.5
Summary: Fixed VHD writer.
Home-page: https://github.com/fujiawei-dev/fixed-vhd-writer
Author: Rustle Karl
Author-email: fu.jiawei@outlook.com
License: MIT
Platform: UNKNOWN
Classifier: Intended Audience :: Developers
Classifier: Environment :: Console
Classifier: License :: OSI Approved :: MIT License
Classifier: Operating System :: OS Independent
Classifier: Programming Language :: Python :: 3
Classifier: Programming Language :: Python :: Implementation :: CPython
Classifier: Programming Language :: Python :: Implementation :: PyPy
Classifier: Topic :: Software Development :: Libraries :: Python Modules
License-File: LICENSE
Requires-Dist: click
